aryanbhatia_101703107_outlier_removal/__init__.py
aryanbhatia_101703107_outlier_removal/outlier.py
aryanbhatia_101703107_outlier_removal-0.0.2.dist-info/LICENSE.txt
aryanbhatia_101703107_outlier_removal-0.0.2.dist-info/METADATA
aryanbhatia_101703107_outlier_removal-0.0.2.dist-info/WHEEL
aryanbhatia_101703107_outlier_removal-0.0.2.dist-info/top_level.txt
aryanbhatia_101703107_outlier_removal-0.0.2.dist-info/RECORD
